astropy_healpix/__init__.py
astropy_healpix/_core.cpython-314t-aarch64-linux-gnu.so
astropy_healpix/bench.py
astropy_healpix/compiler_version.cpython-314t-aarch64-linux-gnu.so
astropy_healpix/conftest.py
astropy_healpix/core.py
astropy_healpix/healpy.py
astropy_healpix/high_level.py
astropy_healpix/setup_package.py
astropy_healpix/utils.py
astropy_healpix/version.py
astropy_healpix/tests/__init__.py
astropy_healpix/tests/test_bench.py
astropy_healpix/tests/test_core.py
astropy_healpix/tests/test_healpy.py
astropy_healpix/tests/test_high_level.py
astropy_healpix/tests/test_utils.py
astropy_healpix-1.1.3.dist-info/METADATA
astropy_healpix-1.1.3.dist-info/WHEEL
astropy_healpix-1.1.3.dist-info/top_level.txt
astropy_healpix-1.1.3.dist-info/RECORD
astropy_healpix-1.1.3.dist-info/licenses/LICENSE.md
