Metadata-Version: 2.4
Name: astropy_healpix
Version: 1.1.3
Summary: BSD-licensed HEALPix for Astropy
Home-page: https://github.com/astropy/astropy-healpix
Author: Astropy Developers
Author-email: astropy.team@gmail.com
License: BSD 3-Clause
Keywords: astronomy,astrophysics,astropy,healpix,coordinates
Classifier: Intended Audience :: Science/Research
Classifier: Operating System :: OS Independent
Classifier: Programming Language :: C
Classifier: Programming Language :: Cython
Classifier: Programming Language :: Python :: 3
Classifier: Programming Language :: Python :: Implementation :: CPython
Classifier: Topic :: Scientific/Engineering :: Astronomy
Classifier: Topic :: Scientific/Engineering :: Physics
Requires-Python: >=3.10
License-File: LICENSE.md
Requires-Dist: numpy>=1.25
Requires-Dist: astropy>=5
Provides-Extra: test
Requires-Dist: pytest-astropy; extra == "test"
Requires-Dist: hypothesis; extra == "test"
Provides-Extra: docs
Requires-Dist: sphinx-astropy; extra == "docs"
Requires-Dist: matplotlib; extra == "docs"
Dynamic: license-file
